st_material_table/__init__.py
st_material_table/_version.py
st_material_table/frontend/build/asset-manifest.json
st_material_table/frontend/build/bootstrap.min.css
st_material_table/frontend/build/index.html
st_material_table/frontend/build/precache-manifest.744afaeb1552df18439b54195d915046.js
st_material_table/frontend/build/service-worker.js
st_material_table/frontend/build/static/js/2.d0448f1b.chunk.js
st_material_table/frontend/build/static/js/2.d0448f1b.chunk.js.LICENSE.txt
st_material_table/frontend/build/static/js/2.d0448f1b.chunk.js.map
st_material_table/frontend/build/static/js/main.b8058af5.chunk.js
st_material_table/frontend/build/static/js/main.b8058af5.chunk.js.map
st_material_table/frontend/build/static/js/runtime-main.928d0424.js
st_material_table/frontend/build/static/js/runtime-main.928d0424.js.map
st_material_table-0.0.4.dist-info/LICENSE
st_material_table-0.0.4.dist-info/METADATA
st_material_table-0.0.4.dist-info/WHEEL
st_material_table-0.0.4.dist-info/top_level.txt
st_material_table-0.0.4.dist-info/RECORD
