Metadata-Version: 2.1
Name: st-material-table
Version: 0.0.4
Summary: Streamlit Custom Components in React
Home-page: https://github.com/icheft/st-material-table
Author: Brian L. Chen
Author-email: brian.lxchen@gmail.com
License: UNKNOWN
Platform: UNKNOWN
Classifier: Programming Language :: Python :: 3
Classifier: License :: OSI Approved :: MIT License
Classifier: Operating System :: OS Independent
Requires-Python: >=3.6
Requires-Dist: numpy
Requires-Dist: pandas
Requires-Dist: streamlit (>=0.83)
